opendma/remote/__init__.py
opendma/remote/rest.py
opendma_remote-0.8.0.dist-info/licenses/LICENSE
opendma_remote-0.8.0.dist-info/METADATA
opendma_remote-0.8.0.dist-info/WHEEL
opendma_remote-0.8.0.dist-info/top_level.txt
opendma_remote-0.8.0.dist-info/RECORD
