Metadata-Version: 2.4
Name: opendma-remote
Version: 0.8.0
Summary: OpenDMA REST client to access OpenDMA repositories via REST
Author: Stefan Kopf, OpenDMA Contributors
Maintainer: Stefan Kopf
License-Expression: MIT
Project-URL: Homepage, https://opendma.org
Project-URL: Repository, https://github.com/OpenDMA/opendma-python-remote.git
Classifier: Development Status :: 4 - Beta
Classifier: Intended Audience :: Developers
Classifier: Programming Language :: Python :: 3.9
Classifier: Programming Language :: Python :: 3.10
Classifier: Programming Language :: Python :: 3.11
Classifier: Programming Language :: Python :: 3.12
Classifier: Programming Language :: Python :: 3.13
Classifier: Programming Language :: Python :: 3.14
Classifier: Programming Language :: Python :: 3.15
Requires-Python: >=3.9
License-File: LICENSE
Requires-Dist: opendma-api>=0.8.0
Requires-Dist: pydantic<3.0.0,>=2.6
Requires-Dist: requests<3,>=2
Requires-Dist: python-dateutil>=2.8.2
Dynamic: license-file
